hello_uv_tkerby/__init__.py
hello_uv_tkerby/core.py
hello_uv_tkerby/main.py
hello_uv_tkerby-0.1.2.dist-info/WHEEL
hello_uv_tkerby-0.1.2.dist-info/METADATA
hello_uv_tkerby-0.1.2.dist-info/RECORD
