Metadata-Version: 2.3
Name: hello-uv-tkerby
Version: 0.1.2
Summary: A tiny demo package
License: MIT
Classifier: Programming Language :: Python :: 3
Classifier: Operating System :: OS Independent
Requires-Dist: numpy>=1.26.0
Requires-Dist: pandas>=2.3.3
Requires-Python: >=3.13
Project-URL: Changelog, https://github.com/me/spam/blob/master/CHANGELOG.md
Project-URL: Documentation, https://readthedocs.org
Project-URL: Homepage, https://example.com
Project-URL: Issues, https://github.com/me/spam/issues
Project-URL: Repository, https://github.com/me/spam.git
